MANIFEST.in
README.rst
setup.py
dragon_sphinx/__init__.py
dragon_sphinx.egg-info/PKG-INFO
dragon_sphinx.egg-info/SOURCES.txt
dragon_sphinx.egg-info/dependency_links.txt
dragon_sphinx.egg-info/not-zip-safe
dragon_sphinx.egg-info/top_level.txt