Metadata-Version: 1.0
Name: dragon-sphinx
Version: 0.1
Summary: Sphinx extensions for the Stupeflix tasks system
Home-page: https://github.com/Stupeflix/dragon-sphinx
Author: Luper Rouch
Author-email: luper.rouch@gmail.com
License: BSD
Keywords: dragon tasks sphinx documentation
Platform: UNKNOWN
